Part 5/e6(Joachim)/f.v
module f(
    input logic[31:0] a,
    output logic r
);

    logic[31:0] i;
    always_comb begin
        i = 12; // Set the I value here
        if (a>i) begin
            r = 1;
        end

        else begin
            r = 0;
        end

    end
endmodule

Part 5/e6(Joachim)/search.v
module search(
    input logic reset,
    input logic clock,
    output logic[31:0] i
);

    logic[31:0] mid;
    logic test;
    logic[31:0] lo, lo_next;
    logic[31:0] hi, hi_next;

    f s(mid, test);
    
    always @(*) begin
     if (lo < hi) begin
        
        
        mid = (lo + hi)/2;
        

        if (test == 1) begin
            hi_next = mid;
            lo_next = lo;
        end
        else begin
            lo_next = mid;
            hi_next = hi;
        end
        i = lo;
     end

    end

    always @(posedge clock) begin 
        if (reset==1) begin
            lo <= 0;
            hi <= 31'h7FFFFFFF; 
        end
        else begin
             lo <= lo_next;
             hi <= hi_next;
        end
    end
    endmodule

Part 5/e6(Joachim)/search_tb.v

module search_tb(    
);
    logic reset, clock;
    logic[31:0] i;
    initial begin
        $dumpfile("search.vcd");
        $dumpvars(0, search_tb);
        clock = 0;

        #5;

        repeat (100000) begin
            #1 clock = !clock;
        end

       
    end

    initial begin
       
        @(posedge clock);
        reset = 1;
        #1;

        @(posedge clock);
        #1;
        reset = 0;

        repeat (100) begin
            @(posedge clock);
            
        end
        $display("i=%d,  time=%t", i, $time);
        
    end
    search se(
        .reset(reset),
        .clock(clock),
        .i(i)
    );
endmodule

Part 5/e6(Joachim)/search.vcd
$date
	Mon Nov  8 21:57:08 2021
$end
$version
	Icarus Verilog
$end
$timescale
	1s
$end
$scope module search_tb $end
$var wire 32 ! i [31:0] $end
$var reg 1 " clock $end
$var reg 1 # reset $end
$scope module se $end
$var wire 1 " clock $end
$var wire 1 # reset $end
$var wire 1 $ test $end
$var reg 32 % hi [31:0] $end
$var reg 32 & hi_next [31:0] $end
$var reg 32 ' i [31:0] $end
$var reg 32 ( lo [31:0] $end
$var reg 32 ) lo_next [31:0] $end
$var reg 32 * mid [31:0] $end
$scope module s $end
$var wire 32 + a [31:0] $end
$var reg 32 , i [31:0] $end
$var reg 1 $ r $end
$upscope $end
$upscope $end
$upscope $end
$enddefinitions $end
#0
$dumpvars
b1100 ,
bx +
bx *
bx )
bx (
bx '
bx &
bx %
0$
x#
0"
bx !
$end
#6
1$
b0 !
b0 '
b111111111111111111111111111111 &
b0 )
b111111111111111111111111111111 *
b111111111111111111111111111111 +
b1111111111111111111111111111111 %
b0 (
1#
1"
#7
0"
#8
1"
#9
0#
0"
#10
b11111111111111111111111111111 &
b11111111111111111111111111111 *
b11111111111111111111111111111 +
b111111111111111111111111111111 %
1"
#11
0"
#12
b1111111111111111111111111111 &
b1111111111111111111111111111 *
b1111111111111111111111111111 +
b11111111111111111111111111111 %
1"
#13
0"
#14
b111111111111111111111111111 &
b111111111111111111111111111 *
b111111111111111111111111111 +
b1111111111111111111111111111 %
1"
#15
0"
#16
b11111111111111111111111111 &
b11111111111111111111111111 *
b11111111111111111111111111 +
b111111111111111111111111111 %
1"
#17
0"
#18
b1111111111111111111111111 &
b1111111111111111111111111 *
b1111111111111111111111111 +
b11111111111111111111111111 %
1"
#19
0"
#20
b111111111111111111111111 &
b111111111111111111111111 *
b111111111111111111111111 +
b1111111111111111111111111 %
1"
#21
0"
#22
b11111111111111111111111 &
b11111111111111111111111 *
b11111111111111111111111 +
b111111111111111111111111 %
1"
#23
0"
#24
b1111111111111111111111 &
b1111111111111111111111 *
b1111111111111111111111 +
b11111111111111111111111 %
1"
#25
0"
#26
b111111111111111111111 &
b111111111111111111111 *
b111111111111111111111 +
b1111111111111111111111 %
1"
#27
0"
#28
b11111111111111111111 &
b11111111111111111111 *
b11111111111111111111 +
b111111111111111111111 %
1"
#29
0"
#30
b1111111111111111111 &
b1111111111111111111 *
b1111111111111111111 +
b11111111111111111111 %
1"
#31
0"
#32
b111111111111111111 &
b111111111111111111 *
b111111111111111111 +
b1111111111111111111 %
1"
#33
0"
#34
b11111111111111111 &
b11111111111111111 *
b11111111111111111 +
b111111111111111111 %
1"
#35
0"
#36
b1111111111111111 &
b1111111111111111 *
b1111111111111111 +
b11111111111111111 %
1"
#37
0"
#38
b111111111111111 &
b111111111111111 *
b111111111111111 +
b1111111111111111 %
1"
#39
0"
#40
b11111111111111 &
b11111111111111 *
b11111111111111 +
b111111111111111 %
1"
#41
0"
#42
b1111111111111 &
b1111111111111 *
b1111111111111 +
b11111111111111 %
1"
#43
0"
#44
b111111111111 &
b111111111111 *
b111111111111 +
b1111111111111 %
1"
#45
0"
#46
b11111111111 &
b11111111111 *
b11111111111 +
b111111111111 %
1"
#47
0"
#48
b1111111111 &
b1111111111 *
b1111111111 +
b11111111111 %
1"
#49
0"
#50
b111111111 &
b111111111 *
b111111111 +
b1111111111 %
1"
#51
0"
#52
b11111111 &
b11111111 *
b11111111 +
b111111111 %
1"
#53
0"
#54
b1111111 &
b1111111 *
b1111111 +
b11111111 %
1"
#55
0"
#56
b111111 &
b111111 *
b111111 +
b1111111 %
1"
#57
0"
#58
b11111 &
b11111 *
b11111 +
b111111 %
1"
#59
0"
#60
b1111 &
b1111 *
b1111 +
b11111 %
1"
#61
0"
#62
b111 )
0$
b1111 &
b111 *
b111 +
b1111 %
1"
#63
0"
#64
b111 !
b111 '
b1011 )
b1011 *
b1011 +
b111 (
1"
#65
0"
#66
b1101 &
1$
b1011 !
b1011 '
b1011 )
b1101 *
b1101 +
b1011 (
1"
#67
0"
#68
b1100 )
0$
b1101 &
b1100 *
b1100 +
b1101 %
1"
#69
0"
#70
b1100 !
b1100 '
b1100 (
1"
